[
  {
    "title": "zanahoria",
    "description": "Es una zanahoria",
    "price": 400,
    "thumbnail": "Sin imagen",
    "code": "zanahoria",
    "stock": 30,
    "status": true,
    "category": "verdura",
    "id": "2"
  },
  {
    "title": "palta",
    "description": "Es una papa",
    "price": 300,
    "thumbnail": "Sin imagen",
    "code": "palta",
    "stock": 25,
    "status": true,
    "category": "verdura",
    "id": "3"
  },
  {
    "title": "camote",
    "description": "es un camote",
    "price": 200,
    "thumbnail": "",
    "code": "camote123",
    "stock": 5,
    "status": true,
    "category": "verdura",
    "id": "2184aa48-91d5-4f63-9d7c-b76e7cbf5231"
  },
  {
    "title": "berenjena",
    "description": "es un berenjena",
    "price": 100,
    "thumbnail": "",
    "code": "berenjena123",
    "stock": 15,
    "status": true,
    "category": "verdura",
    "id": "a8a130cb-b770-45c4-90d2-a3a696522091"
  },
  {
    "title": "manzana",
    "description": "es un manzana",
    "price": 100,
    "thumbnail": "",
    "code": "manzana123",
    "stock": 15,
    "status": true,
    "category": "fruta",
    "id": "77a1efa5-c26b-40eb-8292-bf9c2d3874bc"
  },
  {
    "title": "pera",
    "description": "es un manzana",
    "price": 100,
    "thumbnail": "",
    "code": "pera",
    "stock": 15,
    "status": true,
    "category": "fruta",
    "id": "d928d209-eb87-4311-9f5d-0a1545b414f4"
  },
  {
    "title": "brocoli",
    "description": "es un manzana",
    "price": 100,
    "thumbnail": "",
    "code": "brocoli",
    "stock": 15,
    "status": true,
    "category": "fruta",
    "id": "736c5128-2eeb-428e-9f90-ae036a2e8c3c"
  },
  {
    "title": "papa",
    "description": "Es una papa",
    "price": 300,
    "thumbnail": "Sin imagen",
    "code": "papa123",
    "stock": 25,
    "status": true,
    "category": "verdura",
    "id": "7eac3d92-3190-485c-877b-54adfa8a8295"
  }
]